bookied/__init__.py
bookied/cli.py
bookied/config-default.yaml
bookied/config.py
bookied/endpointschema.py
bookied/exceptions.py
bookied/log.py
bookied/redis_con.py
bookied/schedule.py
bookied/utils.py
bookied/web.py
bookied/work.py
bookied/triggers/__init__.py
bookied/triggers/cancel.py
bookied/triggers/create.py
bookied/triggers/dynamic_bmg.py
bookied/triggers/finish.py
bookied/triggers/in_progress.py
bookied/triggers/result.py
bookied/triggers/trigger.py
bos_auto-0.4.9.dist-info/LICENSE.txt
bos_auto-0.4.9.dist-info/METADATA
bos_auto-0.4.9.dist-info/WHEEL
bos_auto-0.4.9.dist-info/entry_points.txt
bos_auto-0.4.9.dist-info/top_level.txt
bos_auto-0.4.9.dist-info/RECORD
