Metadata-Version: 2.1
Name: bos-auto
Version: 0.4.9
Summary: A daemon to manage synchronization with the blockchain
Home-page: http://pbsa.info
Author: Peerplays Community
Maintainer: Peerplays Community
License: UNKNOWN
Download-URL: https://github.com/pbsa/bos-auto/tarball/0.4.9
Keywords: peerplays,bos
Platform: UNKNOWN
Classifier: License :: OSI Approved :: GNU General Public License v3 (GPLv3)
Classifier: Operating System :: OS Independent
Classifier: Programming Language :: Python :: 3
Classifier: Development Status :: 3 - Alpha
Classifier: Intended Audience :: Developers
Requires-Dist: peerplays
Requires-Dist: bos-sync
Requires-Dist: bos-incidents
Requires-Dist: redis
Requires-Dist: rq
Requires-Dist: click
Requires-Dist: click-datetime
Requires-Dist: jsonschema
Requires-Dist: pyyaml
Requires-Dist: strict-rfc3339
Requires-Dist: flask
Requires-Dist: flask-rq
Requires-Dist: prettytable
Requires-Dist: dateutils
Requires-Dist: colorlog
Requires-Dist: tqdm
Requires-Dist: requests (==2.21.0)
Requires-Dist: python-telegram-handler
Requires-Dist: secp256k1
